<annotation>
	<folder>test</folder>
	<filename>168.jpeg</filename>
	<path>D:\Object_detection_1\models-master\research\images\test\168.jpeg</path>
	<source>
		<database>Unknown</database>
	</source>
	<size>
		<width>284</width>
		<height>177</height>
		<depth>3</depth>
	</size>
	<segmented>0</segmented>
	<object>
		<name>gun</name>
		<pose>Unspecified</pose>
		<truncated>0</truncated>
		<difficult>0</difficult>
		<bndbox>
			<xmin>106</xmin>
			<ymin>77</ymin>
			<xmax>175</xmax>
			<ymax>149</ymax>
		</bndbox>
	</object>
</annotation>
